{"duration":1818,"records":[{"duration":339,"stepId":"io.quarkus.deployment.steps.ConfigGenerationBuildStep#generateConfigClass","started":"06:50:36.665","dependents":[313],"id":299,"thread":"build-20"},{"duration":293,"stepId":"io.quarkus.devui.deployment.BuildTimeContentProcessor#createBuildTimeConstJsTemplate","started":"06:50:36.912","dependents":[301,302],"id":300,"thread":"build-36"},{"duration":253,"stepId":"io.quarkus.vertx.http.deployment.devmode.console.DevConsoleProcessor#setupDeploymentSideHandling","started":"06:50:37.391","dependents":[310,311],"id":309,"thread":"build-36"},{"duration":245,"stepId":"io.quarkus.deployment.console.ConsoleProcessor#setupConsole","started":"06:50:36.057","dependents":[199,195,196,197],"id":194,"thread":"build-28"},{"duration":220,"stepId":"io.quarkus.devui.deployment.DevUIProcessor#getAllExtensions","started":"06:50:36.678","dependents":[294,297,293,295],"id":292,"thread":"build-18"},{"duration":203,"stepId":"io.quarkus.arc.deployment.ArcProcessor#generateResources","started":"06:50:36.662","dependents":[314,313,280,291],"id":279,"thread":"build-31"},{"duration":147,"stepId":"io.quarkus.deployment.index.ApplicationArchiveBuildStep#build","started":"06:50:36.200","dependents":[199,239,232,217,267,287,291,200,203,201,202],"id":198,"thread":"build-31"},{"duration":144,"stepId":"io.quarkus.arc.deployment.ArcProcessor#buildCompatibleExtensions","started":"06:50:35.977","dependents":[232,246],"id":159,"thread":"build-16"},{"duration":129,"stepId":"io.quarkus.vertx.http.deployment.VertxHttpProcessor#bodyHandler","started":"06:50:36.078","dependents":[314,307,298],"id":191,"thread":"build-30"},{"duration":128,"stepId":"io.quarkus.devui.deployment.menu.ConfigurationProcessor#createConfigurationPages","started":"06:50:36.151","dependents":[294],"id":193,"thread":"build-6"},{"duration":125,"stepId":"io.quarkus.deployment.logging.LoggingResourceProcessor#logConsoleCommand","started":"06:50:36.038","dependents":[231],"id":186,"thread":"build-20"},{"duration":113,"stepId":"io.quarkus.deployment.steps.ApplicationIndexBuildStep#build","started":"06:50:36.086","dependents":[256,190,198,246],"id":189,"thread":"build-18"},{"duration":112,"stepId":"io.quarkus.arc.deployment.ArcProcessor#registerBeans","started":"06:50:36.500","dependents":[257,252,250,253,262,248,258,249,251,256,255,259,260],"id":247,"thread":"build-29"},{"duration":110,"stepId":"io.quarkus.devui.deployment.BuildTimeContentProcessor#createIndexHtmlTemplate","started":"06:50:37.206","dependents":[302],"id":301,"thread":"build-20"},{"duration":100,"stepId":"io.quarkus.deployment.steps.MainClassBuildStep#build","started":"06:50:37.645","dependents":[],"id":314,"thread":"build-18"},{"duration":100,"stepId":"io.quarkus.deployment.steps.ConfigDescriptionBuildStep#createConfigDescriptions","started":"06:50:36.051","dependents":[309,188,193],"id":184,"thread":"build-21"},{"duration":96,"stepId":"io.quarkus.vertx.http.deployment.VertxHttpProcessor#preinitializeRouter","started":"06:50:36.114","dependents":[258,257,306,314,259],"id":192,"thread":"build-29"},{"duration":80,"stepId":"io.quarkus.netty.deployment.NettyProcessor#setNettyMachineId","started":"06:50:36.034","dependents":[314],"id":156,"thread":"build-24"},{"duration":79,"stepId":"io.quarkus.deployment.logging.LoggingResourceProcessor#setupLoggingRuntimeInit","started":"06:50:36.366","dependents":[309,314,308,313,298],"id":240,"thread":"build-8"},{"duration":72,"stepId":"io.quarkus.devui.deployment.DevUIProcessor#registerDevUiHandlers","started":"06:50:37.317","dependents":[309,306,314,304],"id":303,"thread":"build-20"},{"duration":72,"stepId":"io.quarkus.vertx.http.deployment.VertxHttpProcessor#logging","started":"06:50:35.994","dependents":[125],"id":122,"thread":"build-6"},{"duration":71,"stepId":"io.quarkus.vertx.http.deployment.HttpSecurityProcessor#initBasicAuth","started":"06:50:36.075","dependents":[258,257,314,259],"id":182,"thread":"build-6"},{"duration":71,"stepId":"io.quarkus.deployment.steps.BannerProcessor#recordBanner","started":"06:50:36.101","dependents":[314,240],"id":187,"thread":"build-31"},{"duration":70,"stepId":"io.quarkus.vertx.core.deployment.VertxCoreProcessor#createVertxContextHandlers","started":"06:50:35.974","dependents":[314,173,148],"id":91,"thread":"build-11"},{"duration":69,"stepId":"io.quarkus.resteasy.common.deployment.ResteasyCommonProcessor#setupProviders","started":"06:50:36.409","dependents":[264,266,242,313],"id":241,"thread":"build-18"},{"duration":69,"stepId":"io.quarkus.devui.deployment.logstream.LogStreamProcessor#handler","started":"06:50:35.977","dependents":[314,240],"id":96,"thread":"build-17"},{"duration":68,"stepId":"io.quarkus.devui.deployment.build.BuildMetricsDevUIProcessor#create","started":"06:50:35.942","dependents":[314],"id":66,"thread":"build-4"},{"duration":68,"stepId":"io.quarkus.vertx.http.deployment.HttpSecurityProcessor#initFormAuth","started":"06:50:36.075","dependents":[258,309,257,306,314,259,304],"id":178,"thread":"build-13"},{"duration":68,"stepId":"io.quarkus.netty.deployment.NettyProcessor#eagerlyInitClass","started":"06:50:35.942","dependents":[314],"id":67,"thread":"build-3"},{"duration":67,"stepId":"io.quarkus.vertx.http.deployment.HttpSecurityProcessor#initMtlsClientAuth","started":"06:50:36.076","dependents":[258,257,314,259],"id":177,"thread":"build-10"},{"duration":66,"stepId":"io.quarkus.vertx.http.deployment.StaticResourcesProcessor#collectStaticResources","started":"06:50:36.349","dependents":[281],"id":239,"thread":"build-29"},{"duration":64,"stepId":"io.quarkus.deployment.dev.HotDeploymentWatchedFileBuildStep#setupWatchedFileHotDeployment","started":"06:50:36.080","dependents":[310,311],"id":179,"thread":"build-27"},{"duration":61,"stepId":"io.quarkus.resteasy.deployment.ResteasyStandaloneBuildStep#addDefaultAuthFailureHandler","started":"06:50:36.048","dependents":[314,307],"id":147,"thread":"build-3"},{"duration":61,"stepId":"io.quarkus.arc.deployment.devconsole.ArcDevConsoleProcessor#exposeArcContainer","started":"06:50:36.085","dependents":[310,314],"id":181,"thread":"build-14"},{"duration":60,"stepId":"io.quarkus.deployment.steps.ConfigGenerationBuildStep#checkForBuildTimeConfigChange","started":"06:50:36.078","dependents":[314],"id":175,"thread":"build-15"},{"duration":57,"stepId":"io.quarkus.vertx.deployment.VertxProcessor#currentContextFactory","started":"06:50:36.080","dependents":[314,279],"id":174,"thread":"build-2"},{"duration":56,"stepId":"io.quarkus.deployment.steps.ConfigGenerationBuildStep#buildTimeRunTimeConfig","started":"06:50:36.078","dependents":[313,299],"id":169,"thread":"build-23"},{"duration":53,"stepId":"io.quarkus.vertx.http.deployment.VertxHttpProcessor#filterMultipleVertxInstancesWarning","started":"06:50:36.033","dependents":[150,240],"id":140,"thread":"build-7"},{"duration":52,"stepId":"io.quarkus.deployment.steps.BootstrapConfigSetupBuildStep#setupBootstrapConfig","started":"06:50:35.994","dependents":[314,97],"id":93,"thread":"build-10"},{"duration":50,"stepId":"io.quarkus.devui.deployment.build.BuildMetricsDevUIProcessor#additionalBeans","started":"06:50:35.961","dependents":[232,246],"id":69,"thread":"build-13"},{"duration":48,"stepId":"io.quarkus.vertx.http.deployment.devmode.ArcDevProcessor#invocationsEndpoint","started":"06:50:35.995","dependents":[309,314,298],"id":88,"thread":"build-9"},{"duration":48,"stepId":"io.quarkus.deployment.steps.PreloadClassesBuildStep#preInit","started":"06:50:35.943","dependents":[314],"id":61,"thread":"build-6"},{"duration":48,"stepId":"io.quarkus.vertx.http.deployment.devmode.console.DevConsoleProcessor#handler","started":"06:50:36.087","dependents":[314,240,298],"id":168,"thread":"build-7"},{"duration":46,"stepId":"io.quarkus.devui.deployment.BuildTimeContentProcessor#gatherMvnpmJars","started":"06:50:36.085","dependents":[301,303],"id":164,"thread":"build-8"},{"duration":43,"stepId":"io.quarkus.vertx.http.deployment.webjar.WebJarProcessor#processWebJarDevMode","started":"06:50:36.899","dependents":[314,296,298,297],"id":295,"thread":"build-25"},{"duration":42,"stepId":"io.quarkus.vertx.http.deployment.devmode.console.ConfigEditorProcessor#config","started":"06:50:36.151","dependents":[310,309,231,314,298],"id":188,"thread":"build-8"},{"duration":41,"stepId":"io.quarkus.deployment.dev.io.NioThreadPoolDevModeProcessor#setupTCCL","started":"06:50:35.974","dependents":[314],"id":74,"thread":"build-2"},{"duration":39,"stepId":"io.quarkus.vertx.core.deployment.VertxCoreProcessor#createVertxThreadFactory","started":"06:50:35.998","dependents":[314,148],"id":82,"thread":"build-8"},{"duration":38,"stepId":"io.quarkus.devui.deployment.BuildTimeContentProcessor#createKnownInternalImportMap","started":"06:50:36.090","dependents":[301],"id":161,"thread":"build-32"},{"duration":38,"stepId":"io.quarkus.arc.deployment.ConfigBuildStep#registerConfigRootsAsBeans","started":"06:50:36.050","dependents":[258,257,259],"id":144,"thread":"build-19"},{"duration":38,"stepId":"io.quarkus.resteasy.deployment.ResteasyBuiltinsProcessor#setupExceptionMapper","started":"06:50:36.107","dependents":[241,314],"id":180,"thread":"build-12"},{"duration":36,"stepId":"io.quarkus.vertx.http.deployment.VertxHttpProcessor#cors","started":"06:50:36.077","dependents":[314,307],"id":152,"thread":"build-26"},{"duration":33,"stepId":"io.quarkus.deployment.steps.ThreadPoolSetup#createExecutor","started":"06:50:36.077","dependents":[176,314,154,167,290,307,173,160],"id":148,"thread":"build-5"},{"duration":32,"stepId":"io.quarkus.arc.deployment.BeanArchiveProcessor#build","started":"06:50:36.376","dependents":[233,241,236,235,242,252,260,237,238,246],"id":232,"thread":"build-31"},{"duration":32,"stepId":"io.quarkus.deployment.steps.BlockingOperationControlBuildStep#blockingOP","started":"06:50:36.015","dependents":[314],"id":94,"thread":"build-19"},{"duration":31,"stepId":"io.quarkus.deployment.console.ConsoleProcessor#helpCommand","started":"06:50:35.945","dependents":[231],"id":47,"thread":"build-5"},{"duration":31,"stepId":"io.quarkus.vertx.deployment.VertxProcessor#autoAddScope","started":"06:50:35.956","dependents":[238],"id":53,"thread":"build-10"},{"duration":28,"stepId":"io.quarkus.deployment.dev.testing.TestTracingProcessor#sharedStateListener","started":"06:50:36.036","dependents":[196],"id":92,"thread":"build-15"},{"duration":28,"stepId":"io.quarkus.deployment.logging.LoggingResourceProcessor#registerMetrics","started":"06:50:36.086","dependents":[314,240],"id":155,"thread":"build-4"},{"duration":28,"stepId":"io.quarkus.deployment.dev.testing.TestTracingProcessor#testConsoleCommand","started":"06:50:36.363","dependents":[231],"id":230,"thread":"build-18"},{"duration":27,"stepId":"io.quarkus.deployment.steps.CapabilityAggregationStep#provideCapabilities","started":"06:50:36.086","dependents":[165],"id":153,"thread":"build-29"},{"duration":26,"stepId":"io.quarkus.smallrye.context.deployment.SmallRyeContextPropagationProcessor#buildStatic","started":"06:50:36.044","dependents":[314],"id":124,"thread":"build-9"},{"duration":26,"stepId":"io.quarkus.arc.deployment.ArcProcessor#validate","started":"06:50:36.631","dependents":[266,265,270,267,268,272,279,291,271,275],"id":264,"thread":"build-31"},{"duration":25,"stepId":"io.quarkus.deployment.pkg.steps.JarResultBuildStep#outputTarget","started":"06:50:36.086","dependents":[162],"id":151,"thread":"build-25"},{"duration":25,"stepId":"io.quarkus.deployment.logging.LoggingResourceProcessor#setUpDefaultLogCleanupFilters","started":"06:50:36.086","dependents":[274],"id":150,"thread":"build-22"},{"duration":24,"stepId":"io.quarkus.vertx.http.deployment.devmode.tests.TestsProcessor#setupTestRoutes","started":"06:50:36.096","dependents":[309,196,306,314,304],"id":158,"thread":"build-19"},{"duration":24,"stepId":"io.quarkus.vertx.core.deployment.VertxCoreProcessor#ioThreadDetector","started":"06:50:35.990","dependents":[314,94],"id":71,"thread":"build-5"},{"duration":23,"stepId":"io.quarkus.vertx.http.deployment.devmode.console.DevConsoleProcessor#collectTemplates","started":"06:50:36.034","dependents":[309],"id":109,"thread":"build-13"},{"duration":22,"stepId":"io.quarkus.vertx.http.deployment.devmode.BuildMetricsDevConsoleProcessor#collectMetrics","started":"06:50:36.057","dependents":[277],"id":131,"thread":"build-22"},{"duration":22,"stepId":"io.quarkus.mutiny.deployment.MutinyProcessor#buildTimeInit","started":"06:50:36.058","dependents":[314],"id":135,"thread":"build-27"},{"duration":21,"stepId":"io.quarkus.arc.deployment.ArcProcessor#loggerProducer","started":"06:50:36.042","dependents":[232,246],"id":117,"thread":"build-26"},{"duration":21,"stepId":"io.quarkus.deployment.steps.ClassTransformingBuildStep#handleClassTransformation","started":"06:50:36.866","dependents":[],"id":291,"thread":"build-36"},{"duration":20,"stepId":"io.quarkus.deployment.console.ConsoleProcessor#quitCommand","started":"06:50:35.956","dependents":[231],"id":46,"thread":"build-7"},{"duration":20,"stepId":"io.quarkus.deployment.steps.DevServicesConfigBuildStep#deprecated","started":"06:50:35.995","dependents":[81],"id":72,"thread":"build-14"},{"duration":19,"stepId":"io.quarkus.vertx.http.deployment.devmode.console.DevConsoleProcessor#setupConsole","started":"06:50:36.110","dependents":[310,311],"id":163,"thread":"build-17"},{"duration":19,"stepId":"io.quarkus.deployment.steps.DevServicesConfigBuildStep#setup","started":"06:50:36.015","dependents":[310,274,311,188,103,193],"id":81,"thread":"build-5"},{"duration":18,"stepId":"io.quarkus.vertx.http.deployment.devmode.console.DevConsoleProcessor#setupDevConsoleRoutes_adbb72d9f4bdcfb494014038ab4871b34b3c24d5","started":"06:50:36.943","dependents":[309,306,314,304],"id":298,"thread":"build-18"},{"duration":17,"stepId":"io.quarkus.arc.deployment.devconsole.ArcDevConsoleProcessor#collectBeanInfo","started":"06:50:36.659","dependents":[309,277,276,298],"id":275,"thread":"build-8"},{"duration":15,"stepId":"io.quarkus.vertx.http.deployment.VertxHttpProcessor#httpRoot","started":"06:50:36.085","dependents":[243,305,287,149,307,163,180],"id":146,"thread":"build-9"},{"duration":15,"stepId":"io.quarkus.vertx.http.deployment.ManagementInterfaceSecurityProcessor#setupAuthenticationMechanisms","started":"06:50:36.135","dependents":[314,232,279,307,246],"id":183,"thread":"build-8"},{"duration":15,"stepId":"io.quarkus.netty.deployment.NettyProcessor#cleanupMacDNSInLog","started":"06:50:35.997","dependents":[150,240],"id":68,"thread":"build-7"},{"duration":14,"stepId":"io.quarkus.vertx.http.deployment.VertxHttpProcessor#frameworkRoot","started":"06:50:36.075","dependents":[309,300,158,294,296,298,303,161,306,301,271,307,163],"id":145,"thread":"build-11"},{"duration":14,"stepId":"io.quarkus.vertx.core.deployment.VertxCoreProcessor#eventLoopCount","started":"06:50:36.051","dependents":[314,312],"id":120,"thread":"build-8"},{"duration":13,"stepId":"io.quarkus.devui.deployment.DevUIProcessor#findAllJsonRPCMethods","started":"06:50:36.364","dependents":[284,300],"id":229,"thread":"build-13"},{"duration":13,"stepId":"io.quarkus.smallrye.context.deployment.SmallRyeContextPropagationProcessor#build","started":"06:50:36.126","dependents":[258,257,314,259],"id":176,"thread":"build-3"},{"duration":13,"stepId":"io.quarkus.netty.deployment.NettyProcessor#cleanupUnsafeLog","started":"06:50:36.033","dependents":[150,240],"id":95,"thread":"build-18"},{"duration":13,"stepId":"io.quarkus.vertx.http.deployment.devmode.console.ConfigEditorProcessor#handleRequests","started":"06:50:36.036","dependents":[309,298],"id":103,"thread":"build-4"},{"duration":12,"stepId":"io.quarkus.devui.deployment.BuildTimeContentProcessor#createBuildTimeData","started":"06:50:36.899","dependents":[300,301],"id":294,"thread":"build-18"},{"duration":12,"stepId":"io.quarkus.netty.deployment.NettyProcessor#registerQualifiers","started":"06:50:36.037","dependents":[232,246],"id":105,"thread":"build-22"},{"duration":12,"stepId":"io.quarkus.vertx.http.deployment.ManagementInterfaceSecurityProcessor#initBasicAuth","started":"06:50:36.053","dependents":[258,257,314,259],"id":121,"thread":"build-23"},{"duration":12,"stepId":"io.quarkus.jackson.deployment.JacksonProcessor#unremovable","started":"06:50:36.364","dependents":[264,266],"id":228,"thread":"build-30"},{"duration":12,"stepId":"io.quarkus.arc.deployment.SyntheticBeansProcessor#initRuntime","started":"06:50:36.614","dependents":[310,314,261,311,262],"id":258,"thread":"build-31"},{"duration":12,"stepId":"io.quarkus.arc.deployment.ArcProcessor#initialize","started":"06:50:36.488","dependents":[247,260,275],"id":246,"thread":"build-8"},{"duration":11,"stepId":"io.quarkus.devui.deployment.menu.ContinuousTestingProcessor#createJsonRPCService","started":"06:50:35.963","dependents":[229,118],"id":43,"thread":"build-15"},{"duration":11,"stepId":"io.quarkus.vertx.http.deployment.devmode.ArcDevProcessor#eventsEndpoint","started":"06:50:36.032","dependents":[309,314,298],"id":90,"thread":"build-21"},{"duration":10,"stepId":"io.quarkus.deployment.steps.ApplicationInfoBuildStep#create","started":"06:50:36.075","dependents":[314],"id":141,"thread":"build-17"},{"duration":9,"stepId":"io.quarkus.jackson.deployment.JacksonProcessor#register","started":"06:50:36.364","dependents":[232,313,246,245],"id":226,"thread":"build-31"},{"duration":9,"stepId":"io.quarkus.deployment.ide.IdeProcessor#detectRunningIdeProcesses","started":"06:50:35.962","dependents":[100],"id":35,"thread":"build-8"},{"duration":9,"stepId":"io.quarkus.mutiny.deployment.MutinyProcessor#runtimeInit","started":"06:50:36.127","dependents":[314],"id":173,"thread":"build-16"},{"duration":9,"stepId":"io.quarkus.arc.deployment.SyntheticBeansProcessor#initRegular","started":"06:50:36.618","dependents":[262],"id":259,"thread":"build-13"},{"duration":9,"stepId":"io.quarkus.arc.deployment.CommandLineArgumentsProcessor#commandLineArgs","started":"06:50:35.946","dependents":[258,257,232,259,246],"id":14,"thread":"build-2"},{"duration":8,"stepId":"io.quarkus.vertx.http.deployment.devmode.console.DevConsoleProcessor#builder","started":"06:50:36.071","dependents":[309,298],"id":133,"thread":"build-29"},{"duration":8,"stepId":"io.quarkus.resteasy.deployment.ResteasyBuiltinsProcessor#vertxProviders","started":"06:50:35.974","dependents":[241],"id":51,"thread":"build-9"},{"duration":8,"stepId":"io.quarkus.deployment.logging.LoggingResourceProcessor#setupLoggingStaticInit","started":"06:50:36.048","dependents":[314],"id":108,"thread":"build-5"},{"duration":8,"stepId":"io.quarkus.resteasy.server.common.deployment.ResteasyServerCommonProcessor#build","started":"06:50:36.479","dependents":[264,266,243,288,313,287,291,246,245],"id":242,"thread":"build-8"},{"duration":8,"stepId":"io.quarkus.deployment.steps.CapabilityAggregationStep#aggregateCapabilities","started":"06:50:36.126","dependents":[239,183,241,171,205,288,166,170,287,172,244,195,223,185,228,219,312,200,246],"id":165,"thread":"build-26"},{"duration":8,"stepId":"io.quarkus.deployment.recording.substitutions.AdditionalSubstitutionsBuildStep#additionalSubstitutions","started":"06:50:36.057","dependents":[314],"id":119,"thread":"build-15"},{"duration":8,"stepId":"io.quarkus.deployment.pkg.steps.PackageTypeVerificationBuildStep#builtins","started":"06:50:36.039","dependents":[102],"id":99,"thread":"build-8"},{"duration":7,"stepId":"io.quarkus.vertx.deployment.VertxProcessor#unremovableBeans","started":"06:50:36.059","dependents":[264,266],"id":123,"thread":"build-5"},{"duration":7,"stepId":"io.quarkus.deployment.steps.CombinedIndexBuildStep#build","started":"06:50:36.351","dependents":[204,206,205,208,227,207,230,244,209,228,210,246,226,241,236,211,212,217,220,248,221,222,223,229,213,214,242,215,255,270,216,290,240,245,224,218],"id":203,"thread":"build-6"},{"duration":7,"stepId":"io.quarkus.deployment.steps.ReflectiveHierarchyStep#build","started":"06:50:36.487","dependents":[313],"id":245,"thread":"build-29"},{"duration":7,"stepId":"io.quarkus.deployment.pkg.steps.FileSystemResourcesBuildStep#notNormalMode","started":"06:50:36.123","dependents":[],"id":162,"thread":"build-22"},{"duration":7,"stepId":"io.quarkus.resteasy.common.deployment.ResteasyCommonProcessor#setupResteasyInjection","started":"06:50:36.870","dependents":[288,314,287],"id":286,"thread":"build-38"},{"duration":6,"stepId":"io.quarkus.devui.deployment.DevUIProcessor#createJsonRpcRouter","started":"06:50:36.867","dependents":[314],"id":284,"thread":"build-15"},{"duration":6,"stepId":"io.quarkus.deployment.steps.ConfigGenerationBuildStep#setupConfigOverride","started":"06:50:35.947","dependents":[],"id":13,"thread":"build-9"},{"duration":6,"stepId":"io.quarkus.deployment.steps.ConfigGenerationBuildStep#watchConfigFiles","started":"06:50:35.982","dependents":[179],"id":55,"thread":"build-7"},{"duration":6,"stepId":"io.quarkus.resteasy.deployment.ResteasyStandaloneBuildStep#boot","started":"06:50:36.879","dependents":[309,306,314,307,304],"id":290,"thread":"build-38"},{"duration":6,"stepId":"io.quarkus.devui.deployment.DevUIProcessor#additionalBean","started":"06:50:36.058","dependents":[232,203,246],"id":118,"thread":"build-13"},{"duration":6,"stepId":"io.quarkus.deployment.steps.CurateOutcomeBuildStep#curateOutcome","started":"06:50:36.078","dependents":[309,300,278,138,181,188,298,164,229,153,165,277,292,198,291,189,139,226,295],"id":137,"thread":"build-4"},{"duration":5,"stepId":"io.quarkus.deployment.index.ApplicationArchiveBuildStep#addConfiguredIndexedDependencies","started":"06:50:36.054","dependents":[198],"id":114,"thread":"build-25"},{"duration":5,"stepId":"io.quarkus.vertx.deployment.VertxProcessor#featureAndCapability","started":"06:50:35.946","dependents":[314,165],"id":11,"thread":"build-7"},{"duration":5,"stepId":"io.quarkus.arc.deployment.ArcProcessor#registerContextPropagation","started":"06:50:36.039","dependents":[124],"id":89,"thread":"build-23"},{"duration":5,"stepId":"io.quarkus.resteasy.server.common.deployment.ResteasyServerCommonProcessor#registerCompatibleAnnotationPrefixes","started":"06:50:36.075","dependents":[242],"id":134,"thread":"build-8"},{"duration":5,"stepId":"io.quarkus.arc.deployment.ArcProcessor#setupExecutor","started":"06:50:36.129","dependents":[314],"id":167,"thread":"build-33"},{"duration":4,"stepId":"io.quarkus.deployment.steps.ReflectiveHierarchyStep#ignoreJavaClassWarnings","started":"06:50:36.058","dependents":[245],"id":115,"thread":"build-11"},{"duration":4,"stepId":"io.quarkus.deployment.steps.ConfigGenerationBuildStep#staticInitSources","started":"06:50:36.058","dependents":[299],"id":116,"thread":"build-2"},{"duration":4,"stepId":"io.quarkus.arc.deployment.SyntheticBeansProcessor#initStatic","started":"06:50:36.614","dependents":[314,262],"id":257,"thread":"build-20"},{"duration":4,"stepId":"io.quarkus.arc.deployment.ConfigBuildStep#registerConfigClasses","started":"06:50:36.657","dependents":[314],"id":273,"thread":"build-20"},{"duration":4,"stepId":"io.quarkus.resteasy.deployment.ResteasyBuiltinsProcessor#addReactiveRoutesExceptionMapper","started":"06:50:36.106","dependents":[314],"id":149,"thread":"build-11"},{"duration":4,"stepId":"io.quarkus.vertx.http.deployment.VertxHttpProcessor#finalizeRouter","started":"06:50:37.391","dependents":[310,314,308,311],"id":307,"thread":"build-20"},{"duration":4,"stepId":"io.quarkus.jackson.deployment.JacksonProcessor#generateCustomizer","started":"06:50:36.371","dependents":[232],"id":227,"thread":"build-20"},{"duration":4,"stepId":"io.quarkus.devui.deployment.menu.ContinuousTestingProcessor#continuousTestingState","started":"06:50:36.871","dependents":[314],"id":285,"thread":"build-6"},{"duration":3,"stepId":"io.quarkus.vertx.http.deployment.devmode.ArcDevProcessor#registerRoutes","started":"06:50:36.659","dependents":[309,306,314,305,279,304],"id":271,"thread":"build-18"},{"duration":3,"stepId":"io.quarkus.vertx.core.deployment.VertxCoreProcessor#build_9fb3ce360263cc99d07c9172ec2feeaa85afcc1a","started":"06:50:36.111","dependents":[192,310,257,314,254,258,157,306,312,281,290,311,259,307],"id":154,"thread":"build-9"},{"duration":3,"stepId":"io.quarkus.arc.deployment.SplitPackageProcessor#splitPackageDetection","started":"06:50:36.351","dependents":[279],"id":201,"thread":"build-30"},{"duration":3,"stepId":"io.quarkus.arc.deployment.ConfigBuildStep#warnStaticInitInjectionPoints","started":"06:50:36.659","dependents":[274],"id":270,"thread":"build-29"},{"duration":3,"stepId":"io.quarkus.jackson.deployment.JacksonProcessor#jacksonSupport","started":"06:50:36.367","dependents":[258,257,314,259],"id":220,"thread":"build-21"},{"duration":3,"stepId":"io.quarkus.deployment.dev.testing.TestTracingProcessor#startTesting","started":"06:50:36.303","dependents":[310,311,240],"id":196,"thread":"build-29"},{"duration":2,"stepId":"io.quarkus.deployment.JniProcessor#setupJni","started":"06:50:36.075","dependents":[132],"id":130,"thread":"build-30"},{"duration":2,"stepId":"io.quarkus.arc.deployment.UnremovableAnnotationsProcessor#unremovableBeans","started":"06:50:36.057","dependents":[264,266],"id":113,"thread":"build-4"},{"duration":2,"stepId":"io.quarkus.deployment.steps.ProfileBuildStep#defaultProfile","started":"06:50:35.962","dependents":[274],"id":34,"thread":"build-9"},{"duration":2,"stepId":"io.quarkus.jackson.deployment.JacksonProcessor#supportMixins","started":"06:50:36.359","dependents":[258,257,314,313,259],"id":204,"thread":"build-18"},{"duration":2,"stepId":"io.quarkus.arc.deployment.ArcProcessor#validateAsyncObserverExceptionHandlers","started":"06:50:36.659","dependents":[279],"id":272,"thread":"build-13"},{"duration":2,"stepId":"io.quarkus.deployment.logging.LoggingResourceProcessor#setMinLevelForInitialConfigurator","started":"06:50:36.051","dependents":[314],"id":107,"thread":"build-15"},{"duration":2,"stepId":"io.quarkus.deployment.steps.NativeImageConfigBuildStep#build","started":"06:50:36.077","dependents":[314],"id":132,"thread":"build-18"},{"duration":2,"stepId":"io.quarkus.vertx.core.deployment.VertxCoreProcessor#preventLoggerContention","started":"06:50:36.057","dependents":[125],"id":112,"thread":"build-10"},{"duration":2,"stepId":"io.quarkus.vertx.http.deployment.devmode.tests.TestsProcessor#handleTestResult","started":"06:50:36.038","dependents":[309,298],"id":86,"thread":"build-3"},{"duration":2,"stepId":"io.quarkus.deployment.logging.LoggingResourceProcessor#setupStackTraceFormatter","started":"06:50:36.347","dependents":[240],"id":199,"thread":"build-29"},{"duration":2,"stepId":"io.quarkus.arc.deployment.staticmethods.InterceptedStaticMethodsProcessor#collectInterceptedStaticMethods","started":"06:50:36.613","dependents":[264,266,260,283],"id":252,"thread":"build-8"},{"duration":2,"stepId":"io.quarkus.vertx.http.deployment.StaticResourcesProcessor#runtimeInit","started":"06:50:36.867","dependents":[314,307],"id":281,"thread":"build-40"},{"duration":1,"stepId":"io.quarkus.vertx.http.deployment.devmode.tests.TestsProcessor#toggleTestRunner","started":"06:50:35.963","dependents":[309,298],"id":33,"thread":"build-14"},{"duration":1,"stepId":"io.quarkus.deployment.steps.ConfigGenerationBuildStep#runtimeDefaultsConfig","started":"06:50:36.663","dependents":[313,299],"id":274,"thread":"build-30"},{"duration":1,"stepId":"io.quarkus.vertx.core.deployment.VertxCoreProcessor#cleanupVertxWarnings","started":"06:50:36.039","dependents":[150,240],"id":87,"thread":"build-5"},{"duration":1,"stepId":"io.quarkus.vertx.http.deployment.devmode.tests.TestsProcessor#runFailedTests","started":"06:50:36.011","dependents":[309,298],"id":70,"thread":"build-19"},{"duration":1,"stepId":"io.quarkus.deployment.console.ConsoleProcessor#setupExceptionHandler","started":"06:50:36.308","dependents":[199],"id":197,"thread":"build-29"},{"duration":1,"stepId":"io.quarkus.vertx.http.deployment.devmode.tests.TestsProcessor#results","started":"06:50:35.946","dependents":[277],"id":9,"thread":"build-8"},{"duration":1,"stepId":"io.quarkus.devui.deployment.logstream.LogStreamProcessor#createJsonRPCService","started":"06:50:35.961","dependents":[229,118],"id":32,"thread":"build-11"},{"duration":1,"stepId":"io.quarkus.resteasy.deployment.ResteasyBuiltinsProcessor#addStaticResourcesExceptionMapper","started":"06:50:36.356","dependents":[314],"id":202,"thread":"build-18"},{"duration":1,"stepId":"io.quarkus.arc.deployment.ReflectiveBeanClassesProcessor#implicitReflectiveBeanClasses","started":"06:50:36.613","dependents":[279],"id":251,"thread":"build-13"},{"duration":1,"stepId":"io.quarkus.deployment.steps.ConfigGenerationBuildStep#builderMappings","started":"06:50:36.657","dependents":[313,299],"id":269,"thread":"build-18"},{"duration":1,"stepId":"io.quarkus.arc.deployment.init.InitializationTaskProcessor#startApplicationInitializer","started":"06:50:36.626","dependents":[314],"id":261,"thread":"build-20"},{"duration":1,"stepId":"io.quarkus.deployment.steps.RegisterForReflectionBuildStep#build","started":"06:50:36.361","dependents":[313,245],"id":205,"thread":"build-30"},{"duration":1,"stepId":"io.quarkus.arc.deployment.ArcProcessor#registerSyntheticObservers","started":"06:50:36.628","dependents":[264,266,263,313,279],"id":262,"thread":"build-20"},{"duration":1,"stepId":"io.quarkus.deployment.steps.ShutdownListenerBuildStep#setupShutdown","started":"06:50:37.396","dependents":[314],"id":308,"thread":"build-18"},{"duration":1,"stepId":"io.quarkus.vertx.deployment.EventBusCodecProcessor#registerCodecs","started":"06:50:36.410","dependents":[313,254],"id":236,"thread":"build-13"},{"duration":1,"stepId":"io.quarkus.deployment.dev.testing.TestTracingProcessor#handle","started":"06:50:36.039","dependents":[150,240],"id":85,"thread":"build-14"},{"duration":1,"stepId":"io.quarkus.devui.deployment.BuildTimeContentProcessor#loadAllBuildTimeTemplates","started":"06:50:37.316","dependents":[303],"id":302,"thread":"build-36"},{"duration":1,"stepId":"io.quarkus.arc.deployment.devui.ArcDevUIProcessor#createJsonRPCService","started":"06:50:35.975","dependents":[229,118],"id":45,"thread":"build-14"},{"duration":1,"stepId":"io.quarkus.arc.deployment.ArcProcessor#unremovableAsyncObserverExceptionHandlers","started":"06:50:35.942","dependents":[264,266],"id":4,"thread":"build-2"},{"duration":1,"stepId":"io.quarkus.arc.deployment.StartupBuildSteps#addScope","started":"06:50:35.982","dependents":[238],"id":52,"thread":"build-12"},{"duration":1,"stepId":"io.quarkus.deployment.steps.MainClassBuildStep#mainClassBuildStep","started":"06:50:36.365","dependents":[],"id":217,"thread":"build-33"},{"duration":1,"stepId":"io.quarkus.arc.deployment.AutoAddScopeProcessor#annotationTransformer","started":"06:50:36.413","dependents":[264,266,246],"id":238,"thread":"build-30"},{"duration":1,"stepId":"io.quarkus.resteasy.deployment.ResteasyBuiltinsProcessor#setUpSecurity","started":"06:50:36.135","dependents":[241,232,246],"id":171,"thread":"build-17"},{"duration":1,"stepId":"io.quarkus.vertx.core.deployment.VertxCoreProcessor#overrideContextInternalInterfaceToAddSafeGuards","started":"06:50:35.940","dependents":[291],"id":1,"thread":"build-3"},{"duration":1,"stepId":"io.quarkus.devui.deployment.menu.BuildMetricsProcessor#createBuildMetricsPages","started":"06:50:35.939","dependents":[294],"id":2,"thread":"build-2"},{"duration":1,"stepId":"io.quarkus.vertx.deployment.VertxProcessor#build","started":"06:50:36.616","dependents":[310,314,313,311],"id":254,"thread":"build-8"},{"duration":1,"stepId":"io.quarkus.netty.deployment.NettyProcessor#registerEventLoopBeans","started":"06:50:36.115","dependents":[258,257,314,259],"id":157,"thread":"build-24"},{"duration":1,"stepId":"io.quarkus.arc.deployment.ArcProcessor#signalBeanContainerReady","started":"06:50:36.866","dependents":[284,286,285,282,314,281,311,307,283],"id":280,"thread":"build-13"},{"duration":1,"stepId":"io.quarkus.vertx.http.deployment.VertxHttpProcessor#initializeRouter","started":"06:50:37.389","dependents":[314,307],"id":306,"thread":"build-18"},{"duration":0,"stepId":"io.quarkus.arc.deployment.BuildTimeEnabledProcessor#unlessBuildProperty","started":"06:50:36.365","dependents":[242,225],"id":213,"thread":"build-8"},{"duration":0,"stepId":"io.quarkus.vertx.deployment.VertxProcessor#registerVerticleClasses","started":"06:50:36.364","dependents":[313],"id":211,"thread":"build-8"},{"duration":0,"stepId":"io.quarkus.deployment.steps.ConfigGenerationBuildStep#suppressNonRuntimeConfigChanged","started":"06:50:35.957","dependents":[175],"id":19,"thread":"build-2"},{"duration":0,"stepId":"io.quarkus.arc.deployment.devconsole.ArcDevConsoleProcessor#monitor","started":"06:50:36.085","dependents":[310,232,246],"id":138,"thread":"build-25"},{"duration":0,"stepId":"io.quarkus.undertow.deployment.UndertowStaticResourcesBuildStep#scanStaticResources","started":"06:50:36.351","dependents":[],"id":200,"thread":"build-28"},{"duration":0,"stepId":"io.quarkus.devui.deployment.menu.ExtensionsProcessor#createExtensionsPages","started":"06:50:36.898","dependents":[294],"id":293,"thread":"build-36"},{"duration":0,"stepId":"io.quarkus.netty.deployment.NettyProcessor#build","started":"06:50:36.075","dependents":[313,132],"id":127,"thread":"build-2"},{"duration":0,"stepId":"io.quarkus.deployment.dev.IsolatedDevModeMain$5$1@780ecd13","started":"06:50:35.944","dependents":[246],"id":6,"thread":"build-5"},{"duration":0,"stepId":"io.quarkus.deployment.console.ConsoleProcessor#installCliCommands","started":"06:50:36.392","dependents":[310,311],"id":231,"thread":"build-13"},{"duration":0,"stepId":"io.quarkus.resteasy.common.deployment.ResteasyCommonProcessor#addStaticInitConfigSourceProvider","started":"06:50:36.135","dependents":[313,299],"id":166,"thread":"build-22"},{"duration":0,"stepId":"io.quarkus.vertx.http.deployment.ManagementInterfaceSecurityProcessor#builtins","started":"06:50:36.049","dependents":[232,246],"id":104,"thread":"build-18"},{"duration":0,"stepId":"io.quarkus.resteasy.deployment.ResteasyServletProcessor#webXmlMapping","started":"06:50:35.990","dependents":[242],"id":57,"thread":"build-9"},{"duration":0,"stepId":"io.quarkus.resteasy.server.common.deployment.ResteasyServerCommonProcessor#beanDefiningAnnotations","started":"06:50:36.075","dependents":[129,232,138,246],"id":126,"thread":"build-15"},{"duration":0,"stepId":"io.quarkus.devui.deployment.logstream.LogStreamProcessor#additionalBean","started":"06:50:36.033","dependents":[232,246],"id":78,"thread":"build-14"},{"duration":0,"stepId":"io.quarkus.arc.deployment.ConfigBuildStep#additionalBeans","started":"06:50:35.957","dependents":[232,246],"id":21,"thread":"build-11"},{"duration":0,"stepId":"io.quarkus.resteasy.common.deployment.ResteasyCommonProcessor#configInjectionStaticInitProvider","started":"06:50:36.089","dependents":[270],"id":143,"thread":"build-32"},{"duration":0,"stepId":"io.quarkus.deployment.CollectionClassProcessor#setupCollectionClasses","started":"06:50:35.981","dependents":[313],"id":48,"thread":"build-8"},{"duration":0,"stepId":"io.quarkus.deployment.steps.CurateOutcomeBuildStep#removeResources","started":"06:50:36.085","dependents":[291],"id":139,"thread":"build-22"},{"duration":0,"stepId":"io.quarkus.arc.deployment.ConfigBuildStep#validateConfigMappingsInjectionPoints","started":"06:50:36.657","dependents":[273,269,299],"id":266,"thread":"build-13"},{"duration":0,"stepId":"io.quarkus.arc.deployment.ConfigBuildStep#vetoMPConfigProperties","started":"06:50:35.994","dependents":[246],"id":63,"thread":"build-8"},{"duration":0,"stepId":"io.quarkus.deployment.steps.MainClassBuildStep#applicationReflection","started":"06:50:35.956","dependents":[313],"id":17,"thread":"build-2"},{"duration":0,"stepId":"io.quarkus.arc.deployment.TestsAsBeansProcessor#testAnnotations","started":"06:50:36.058","dependents":[129,232,138,246],"id":111,"thread":"build-14"},{"duration":0,"stepId":"io.quarkus.smallrye.context.deployment.SmallRyeContextPropagationProcessor#registerBean","started":"06:50:35.956","dependents":[232,246],"id":16,"thread":"build-9"},{"duration":0,"stepId":"io.quarkus.arc.deployment.HotDeploymentConfigBuildStep#startup","started":"06:50:35.957","dependents":[23],"id":22,"thread":"build-12"},{"duration":0,"stepId":"io.quarkus.deployment.ide.IdeProcessor#effectiveIde","started":"06:50:36.048","dependents":[199,309,133,197],"id":100,"thread":"build-17"},{"duration":0,"stepId":"io.quarkus.deployment.steps.AdditionalClassLoaderResourcesBuildStep#appendAdditionalClassloaderResources","started":"06:50:36.032","dependents":[203],"id":76,"thread":"build-14"},{"duration":0,"stepId":"io.quarkus.arc.deployment.staticmethods.InterceptedStaticMethodsProcessor#callInitializer","started":"06:50:36.872","dependents":[314],"id":283,"thread":"build-32"},{"duration":0,"stepId":"io.quarkus.vertx.deployment.VertxProcessor#collectEventConsumers","started":"06:50:36.615","dependents":[254,262],"id":253,"thread":"build-18"},{"duration":0,"stepId":"io.quarkus.resteasy.jackson.deployment.ResteasyJacksonProcessor#feature","started":"06:50:36.034","dependents":[314],"id":80,"thread":"build-4"},{"duration":0,"stepId":"io.quarkus.netty.deployment.NettyProcessor#limitArenaSize","started":"06:50:36.040","dependents":[314],"id":84,"thread":"build-2"},{"duration":0,"stepId":"io.quarkus.vertx.http.deployment.HttpSecurityProcessor#builtins","started":"06:50:36.368","dependents":[314,219,232,313,246],"id":218,"thread":"build-28"},{"duration":0,"stepId":"io.quarkus.arc.deployment.TestsAsBeansProcessor#testClassBeans","started":"06:50:36.039","dependents":[232,246],"id":83,"thread":"build-2"},{"duration":0,"stepId":"io.quarkus.arc.deployment.ArcProcessor#quarkusApplication","started":"06:50:36.363","dependents":[232,246],"id":207,"thread":"build-30"},{"duration":0,"stepId":"io.quarkus.vertx.http.deployment.devmode.console.DevConsoleProcessor#setupWebJar","started":"06:50:35.971","dependents":[295],"id":36,"thread":"build-8"},{"duration":0,"stepId":"io.quarkus.deployment.ide.IdeProcessor#detectIdeFiles","started":"06:50:35.952","dependents":[100],"id":12,"thread":"build-10"},{"duration":0,"stepId":"io.quarkus.deployment.steps.PreloadClassesBuildStep#registerPreInitClasses","started":"06:50:35.974","dependents":[],"id":44,"thread":"build-8"},{"duration":0,"stepId":"io.quarkus.smallrye.context.deployment.SmallRyeContextPropagationProcessor#createSynthBeansForConfiguredInjectionPoints","started":"06:50:36.613","dependents":[258,257,314,259],"id":250,"thread":"build-30"},{"duration":0,"stepId":"io.quarkus.arc.deployment.ArcProcessor#marker","started":"06:50:36.015","dependents":[198],"id":73,"thread":"build-18"},{"duration":0,"stepId":"io.quarkus.deployment.ExtensionLoader#config","started":"06:50:35.995","dependents":[89,84,266,194,108,101,314,232,120,107,287,114,100,104,144,281,106,291,102,184,139,246,192,183,196,121,241,147,234,138,220,130,223,286,306,256,265,242,219,141,271,169,307,299,146,182,148,309,134,235,154,166,126,178,298,172,152,201,303,129,127,209,145,136,269,198,189,137,177,295,274,217,128,187,191,276,279,174,175,143,142,168,308,151,312,290,240,311,155,224,218],"id":64,"thread":"build-12"},{"duration":0,"stepId":"io.quarkus.deployment.logging.LoggingResourceProcessor#setProperty","started":"06:50:35.942","dependents":[314],"id":3,"thread":"build-4"},{"duration":0,"stepId":"io.quarkus.arc.deployment.ArcProcessor#quarkusMain","started":"06:50:36.047","dependents":[129,232,138,246],"id":98,"thread":"build-25"},{"duration":0,"stepId":"io.quarkus.devui.deployment.DevUIProcessor#createAllRoutes","started":"06:50:36.947","dependents":[303],"id":297,"thread":"build-38"},{"duration":0,"stepId":"io.quarkus.smallrye.context.deployment.SmallRyeContextPropagationProcessor#transformInjectionPoint","started":"06:50:36.032","dependents":[246],"id":77,"thread":"build-2"},{"duration":0,"stepId":"io.quarkus.undertow.deployment.UndertowStaticResourcesBuildStep#handleGeneratedWebResources","started":"06:50:36.160","dependents":[],"id":185,"thread":"build-33"},{"duration":0,"stepId":"io.quarkus.resteasy.common.deployment.ResteasyCommonProcessor#disableDefaultExceptionMapper","started":"06:50:36.086","dependents":[314],"id":142,"thread":"build-17"},{"duration":0,"stepId":"io.quarkus.arc.deployment.AutoInjectFieldProcessor#autoInjectQualifiers","started":"06:50:36.408","dependents":[242,234,238],"id":233,"thread":"build-13"},{"duration":0,"stepId":"io.quarkus.deployment.steps.BannerProcessor#watchBannerChanges","started":"06:50:36.075","dependents":[179],"id":128,"thread":"build-14"},{"duration":0,"stepId":"io.quarkus.vertx.http.deployment.devmode.console.DevConsoleProcessor#setupDevConsoleRoutes_8bb86a3e770caadb970f4facb490e30df7a2a187","started":"06:50:36.943","dependents":[309,306,314,304],"id":296,"thread":"build-18"},{"duration":0,"stepId":"io.quarkus.arc.deployment.ArcProcessor#exposeCustomScopeNames","started":"06:50:35.981","dependents":[129,209,235,256,242,232,138,52,238,246],"id":49,"thread":"build-5"},{"duration":0,"stepId":"io.quarkus.vertx.http.deployment.VertxHttpProcessor#additionalBeans","started":"06:50:36.033","dependents":[232,246],"id":79,"thread":"build-2"},{"duration":0,"stepId":"io.quarkus.deployment.logging.LoggingResourceProcessor#setUpDarkeningDefault","started":"06:50:35.943","dependents":[274],"id":5,"thread":"build-2"},{"duration":0,"stepId":"io.quarkus.resteasy.server.common.deployment.ResteasyServerCommonProcessor#processPathInterfaceImplementors","started":"06:50:36.363","dependents":[264,266,232,246],"id":209,"thread":"build-30"},{"duration":0,"stepId":"io.quarkus.arc.deployment.BuildTimeEnabledProcessor#ifBuildProfile","started":"06:50:36.366","dependents":[242,225],"id":215,"thread":"build-8"},{"duration":0,"stepId":"io.quarkus.deployment.steps.DevModeBuildStep#watchChanges","started":"06:50:36.048","dependents":[179],"id":101,"thread":"build-14"},{"duration":0,"stepId":"io.quarkus.arc.deployment.WrongAnnotationUsageProcessor#detect","started":"06:50:36.618","dependents":[279],"id":256,"thread":"build-8"},{"duration":0,"stepId":"io.quarkus.deployment.dev.ConfigureDisableInstrumentationBuildStep#configure","started":"06:50:35.958","dependents":[310,311],"id":23,"thread":"build-11"},{"duration":0,"stepId":"io.quarkus.vertx.core.deployment.VertxCoreProcessor#build_9d6b7122fb368970c50c3a870d1f672392cd8afb","started":"06:50:35.973","dependents":[313,132],"id":41,"thread":"build-14"},{"duration":0,"stepId":"io.quarkus.deployment.logging.LoggingWithPanacheProcessor#process","started":"06:50:36.364","dependents":[291],"id":210,"thread":"build-28"},{"duration":0,"stepId":"io.quarkus.arc.deployment.ConfigBuildStep#registerCustomConfigBeanTypes","started":"06:50:36.613","dependents":[258,257,313,259],"id":249,"thread":"build-13"},{"duration":0,"stepId":"io.quarkus.vertx.http.deployment.devmode.console.DevConsoleProcessor#setupDevConsoleWebjar","started":"06:50:35.945","dependents":[295],"id":7,"thread":"build-7"},{"duration":0,"stepId":"io.quarkus.arc.deployment.BuildTimeEnabledProcessor#conditionTransformer","started":"06:50:36.372","dependents":[246],"id":225,"thread":"build-21"},{"duration":0,"stepId":"io.quarkus.vertx.http.deployment.HttpSecurityProcessor#setupAuthenticationMechanisms","started":"06:50:36.368","dependents":[314,232,279,307,246],"id":219,"thread":"build-6"},{"duration":0,"stepId":"io.quarkus.vertx.http.deployment.devmode.console.DevConsoleProcessor#config","started":"06:50:35.990","dependents":[277],"id":60,"thread":"build-10"},{"duration":0,"stepId":"io.quarkus.deployment.console.ConsoleProcessor#missingDevUIMessageHandler","started":"06:50:36.303","dependents":[310,311],"id":195,"thread":"build-6"},{"duration":0,"stepId":"io.quarkus.vertx.http.deployment.devmode.console.DevConsoleProcessor#runtimeTemplates","started":"06:50:37.645","dependents":[314],"id":310,"thread":"build-18"},{"duration":0,"stepId":"io.quarkus.resteasy.server.common.deployment.ResteasyLogFilterBuildStep#setupLogFilters","started":"06:50:35.973","dependents":[150,240],"id":40,"thread":"build-12"},{"duration":0,"stepId":"io.quarkus.vertx.core.deployment.VertxCoreProcessor#doNotRemoveVertxOptionsCustomizers","started":"06:50:35.989","dependents":[264,266],"id":56,"thread":"build-14"},{"duration":0,"stepId":"io.quarkus.devui.deployment.build.BuildMetricsDevUIProcessor#createJsonRPCService","started":"06:50:36.058","dependents":[229,118],"id":110,"thread":"build-18"},{"duration":0,"stepId":"io.quarkus.arc.deployment.ConfigBuildStep#registerConfigMappingsBean","started":"06:50:36.618","dependents":[262],"id":255,"thread":"build-18"},{"duration":0,"stepId":"io.quarkus.deployment.steps.ConfigGenerationBuildStep#extensionMappings","started":"06:50:36.372","dependents":[266,265,313,255,270,248],"id":224,"thread":"build-33"},{"duration":0,"stepId":"io.quarkus.resteasy.deployment.RestPathAnnotationProcessor#findRestPaths","started":"06:50:36.487","dependents":[246],"id":244,"thread":"build-30"},{"duration":0,"stepId":"io.quarkus.arc.deployment.ConfigBuildStep#validateConfigInjectionPoints","started":"06:50:36.658","dependents":[282],"id":268,"thread":"build-8"},{"duration":0,"stepId":"io.quarkus.vertx.http.deployment.devmode.tests.TestsProcessor#toggleInstrumentation","started":"06:50:35.974","dependents":[309,298],"id":42,"thread":"build-12"},{"duration":0,"stepId":"io.quarkus.deployment.ForkJoinPoolProcessor#setProperty","started":"06:50:35.961","dependents":[314],"id":24,"thread":"build-8"},{"duration":0,"stepId":"io.quarkus.resteasy.deployment.ResteasyServletProcessor#addServletsToExceptionMapper","started":"06:50:36.878","dependents":[314],"id":289,"thread":"build-13"},{"duration":0,"stepId":"io.quarkus.arc.deployment.StartupBuildSteps#registerStartupObservers","started":"06:50:36.630","dependents":[264],"id":263,"thread":"build-13"},{"duration":0,"stepId":"io.quarkus.vertx.http.deployment.devmode.tests.TestsProcessor#toggleTestOutput","started":"06:50:35.994","dependents":[309,298],"id":62,"thread":"build-12"},{"duration":0,"stepId":"io.quarkus.vertx.http.deployment.devmode.tests.TestsProcessor#runAllTests","started":"06:50:35.972","dependents":[309,298],"id":37,"thread":"build-2"},{"duration":0,"stepId":"io.quarkus.arc.deployment.ArcProcessor#launchMode","started":"06:50:35.963","dependents":[232,246],"id":31,"thread":"build-2"},{"duration":0,"stepId":"io.quarkus.arc.deployment.ObserverValidationProcessor#validateApplicationObserver","started":"06:50:36.657","dependents":[279],"id":267,"thread":"build-8"},{"duration":0,"stepId":"io.quarkus.arc.deployment.LoggingBeanSupportProcessor#discoveredComponents","started":"06:50:36.032","dependents":[129,232,138,246],"id":75,"thread":"build-18"},{"duration":0,"stepId":"io.quarkus.arc.deployment.ConfigBuildStep#validateConfigPropertiesInjectionPoints","started":"06:50:36.657","dependents":[273],"id":265,"thread":"build-20"},{"duration":0,"stepId":"io.quarkus.devui.deployment.BuildTimeContentProcessor#mapPageBuildTimeData","started":"06:50:36.680","dependents":[300],"id":278,"thread":"build-8"},{"duration":0,"stepId":"io.quarkus.arc.deployment.HotDeploymentConfigBuildStep#configFile","started":"06:50:35.957","dependents":[179],"id":18,"thread":"build-9"},{"duration":0,"stepId":"io.quarkus.arc.deployment.BuildTimeEnabledProcessor#unlessBuildProfile","started":"06:50:36.370","dependents":[242,225],"id":221,"thread":"build-14"},{"duration":0,"stepId":"io.quarkus.deployment.pkg.steps.PackageTypeVerificationBuildStep#verify","started":"06:50:36.048","dependents":[310,311],"id":102,"thread":"build-11"},{"duration":0,"stepId":"io.quarkus.arc.deployment.ConfigBuildStep#validateConfigValues","started":"06:50:36.872","dependents":[314,313],"id":282,"thread":"build-14"},{"duration":0,"stepId":"io.quarkus.deployment.logging.LoggingResourceProcessor#setupLogFilters","started":"06:50:35.945","dependents":[150,240],"id":8,"thread":"build-8"},{"duration":0,"stepId":"io.quarkus.arc.deployment.AutoProducerMethodsProcessor#annotationTransformer","started":"06:50:36.411","dependents":[246],"id":235,"thread":"build-30"},{"duration":0,"stepId":"io.quarkus.vertx.http.deployment.VertxHttpProcessor#notFoundRoutes","started":"06:50:37.389","dependents":[305],"id":304,"thread":"build-25"},{"duration":0,"stepId":"io.quarkus.deployment.steps.RuntimeConfigSetupBuildStep#setupRuntimeConfig","started":"06:50:36.046","dependents":[192,121,314,120,154,191,187,178,152,175,306,308,312,281,290,311,240,307,182,148,177],"id":97,"thread":"build-15"},{"duration":0,"stepId":"io.quarkus.devui.deployment.menu.DevServicesProcessor#createDevServicesPages","started":"06:50:35.962","dependents":[294],"id":28,"thread":"build-12"},{"duration":0,"stepId":"io.quarkus.deployment.SslProcessor#setupNativeSsl","started":"06:50:36.053","dependents":[132],"id":106,"thread":"build-10"},{"duration":0,"stepId":"io.quarkus.vertx.http.deployment.VertxHttpProcessor#config","started":"06:50:35.961","dependents":[299],"id":25,"thread":"build-12"},{"duration":0,"stepId":"io.quarkus.resteasy.deployment.ResteasyStandaloneBuildStep#staticInit","started":"06:50:36.878","dependents":[314,290],"id":287,"thread":"build-31"},{"duration":0,"stepId":"io.quarkus.deployment.steps.ConfigBuildSteps#generateConfigSources","started":"06:50:35.996","dependents":[],"id":65,"thread":"build-15"},{"duration":0,"stepId":"io.quarkus.arc.deployment.BuildTimeEnabledProcessor#ifBuildProperty","started":"06:50:36.362","dependents":[242,225],"id":206,"thread":"build-18"},{"duration":0,"stepId":"io.quarkus.vertx.http.deployment.devmode.tests.TestsProcessor#forceRestart","started":"06:50:35.981","dependents":[309,298],"id":50,"thread":"build-12"},{"duration":0,"stepId":"io.quarkus.arc.deployment.ArcProcessor#feature","started":"06:50:35.962","dependents":[314],"id":29,"thread":"build-2"},{"duration":0,"stepId":"io.quarkus.deployment.recording.AnnotationProxyBuildStep#build","started":"06:50:36.200","dependents":[254],"id":190,"thread":"build-8"},{"duration":0,"stepId":"io.quarkus.vertx.core.deployment.VertxCoreProcessor#registerVerticleClasses","started":"06:50:36.370","dependents":[313],"id":222,"thread":"build-12"},{"duration":0,"stepId":"io.quarkus.arc.deployment.LookupConditionsProcessor#suppressConditionsGenerators","started":"06:50:36.413","dependents":[246],"id":237,"thread":"build-13"},{"duration":0,"stepId":"io.quarkus.jackson.deployment.JacksonProcessor#autoRegisterModules","started":"06:50:36.366","dependents":[227],"id":214,"thread":"build-8"},{"duration":0,"stepId":"io.quarkus.resteasy.deployment.ResteasyBuiltinsProcessor#addAdditionalEndpointsExceptionMapper","started":"06:50:37.390","dependents":[314],"id":305,"thread":"build-20"},{"duration":0,"stepId":"io.quarkus.arc.deployment.ConfigBuildStep#generateConfigProperties","started":"06:50:36.365","dependents":[266,265,313,255,270,248],"id":212,"thread":"build-20"},{"duration":0,"stepId":"io.quarkus.arc.deployment.devui.ArcDevUIProcessor#pages","started":"06:50:36.677","dependents":[278,292],"id":276,"thread":"build-13"},{"duration":0,"stepId":"io.quarkus.resteasy.deployment.ResteasyServletProcessor#build","started":"06:50:36.878","dependents":[314,313,289],"id":288,"thread":"build-6"},{"duration":0,"stepId":"io.quarkus.resteasy.deployment.ResteasyServletProcessor#jaxrsConfig","started":"06:50:36.487","dependents":[244],"id":243,"thread":"build-18"},{"duration":0,"stepId":"io.quarkus.arc.deployment.ExecutorServiceProcessor#executorServiceBean","started":"06:50:36.127","dependents":[258,257,259],"id":160,"thread":"build-9"},{"duration":0,"stepId":"io.quarkus.arc.deployment.LifecycleEventsBuildStep#startupEvent","started":"06:50:37.645","dependents":[314,312],"id":311,"thread":"build-20"},{"duration":0,"stepId":"io.quarkus.deployment.steps.ConfigGenerationBuildStep#mappings","started":"06:50:36.363","dependents":[266,265,313,255,270,248],"id":208,"thread":"build-18"},{"duration":0,"stepId":"io.quarkus.resteasy.common.deployment.ResteasyCommonProcessor#setupGzipProviders","started":"06:50:36.078","dependents":[241],"id":136,"thread":"build-25"},{"duration":0,"stepId":"io.quarkus.deployment.ConstructorPropertiesProcessor#build","started":"06:50:36.366","dependents":[313],"id":216,"thread":"build-8"},{"duration":0,"stepId":"io.quarkus.arc.deployment.StartupBuildSteps#unremovableBeans","started":"06:50:35.972","dependents":[264,266],"id":38,"thread":"build-9"},{"duration":0,"stepId":"io.quarkus.arc.deployment.ConfigBuildStep#registerConfigPropertiesBean","started":"06:50:36.613","dependents":[262],"id":248,"thread":"build-31"},{"duration":0,"stepId":"io.quarkus.resteasy.common.deployment.ResteasyCommonProcessor#registerJsonContextResolvers","started":"06:50:36.371","dependents":[264,266,241,232,246],"id":223,"thread":"build-27"},{"duration":0,"stepId":"io.quarkus.vertx.core.deployment.VertxCoreProcessor#filterNettyHostsFileParsingWarn","started":"06:50:35.963","dependents":[150,240],"id":30,"thread":"build-12"},{"duration":0,"stepId":"io.quarkus.resteasy.common.deployment.ResteasyCommonProcessor#resteasyConfig","started":"06:50:36.136","dependents":[241],"id":172,"thread":"build-7"},{"duration":0,"stepId":"io.quarkus.arc.deployment.ArcProcessor#convertLegacyAdditionalStereotypes","started":"06:50:35.956","dependents":[235,246],"id":15,"thread":"build-8"},{"duration":0,"stepId":"io.quarkus.arc.deployment.staticmethods.InterceptedStaticMethodsProcessor#processInterceptedStaticMethods","started":"06:50:36.628","dependents":[313,291],"id":260,"thread":"build-13"},{"duration":0,"stepId":"io.quarkus.vertx.http.deployment.VertxHttpProcessor#openSocket","started":"06:50:37.645","dependents":[314,313],"id":312,"thread":"build-25"},{"duration":0,"stepId":"io.quarkus.arc.deployment.AutoInjectFieldProcessor#annotationTransformer","started":"06:50:36.409","dependents":[246],"id":234,"thread":"build-18"},{"duration":0,"stepId":"io.quarkus.vertx.http.deployment.devmode.tests.TestsProcessor#toggleLiveReloadEnabled","started":"06:50:35.988","dependents":[309,298],"id":54,"thread":"build-15"},{"duration":0,"stepId":"io.quarkus.vertx.deployment.VertxProcessor#registerBean","started":"06:50:35.951","dependents":[232,246],"id":10,"thread":"build-8"},{"duration":0,"stepId":"io.quarkus.deployment.ExtensionLoader#booleanSupplierFactory","started":"06:50:35.961","dependents":[153],"id":27,"thread":"build-9"},{"duration":0,"stepId":"io.quarkus.devui.deployment.menu.ContinuousTestingProcessor#createContinuousTestingPages","started":"06:50:35.990","dependents":[294],"id":58,"thread":"build-8"},{"duration":0,"stepId":"io.quarkus.deployment.logging.LoggingResourceProcessor#setUpDefaultLevels","started":"06:50:36.070","dependents":[274,240],"id":125,"thread":"build-23"},{"duration":0,"stepId":"io.quarkus.vertx.http.deployment.devmode.tests.TestsProcessor#printfailures","started":"06:50:35.961","dependents":[309,298],"id":26,"thread":"build-2"},{"duration":0,"stepId":"io.quarkus.vertx.http.deployment.devmode.console.DevConsoleProcessor#buildTimeTemplates","started":"06:50:36.677","dependents":[310,311],"id":277,"thread":"build-30"},{"duration":0,"stepId":"io.quarkus.devui.deployment.menu.ConfigurationProcessor#registerJsonRpcService","started":"06:50:35.972","dependents":[229,118],"id":39,"thread":"build-11"},{"duration":0,"stepId":"io.quarkus.arc.deployment.devui.ArcDevUIProcessor#registerMonitoringComponents","started":"06:50:36.075","dependents":[232,246],"id":129,"thread":"build-18"},{"duration":0,"stepId":"io.quarkus.resteasy.deployment.RestPathAnnotationProcessor#registerBeanClasses","started":"06:50:36.135","dependents":[232,246],"id":170,"thread":"build-23"},{"duration":0,"stepId":"io.quarkus.vertx.http.deployment.devmode.tests.TestsProcessor#handleTestStatus","started":"06:50:35.956","dependents":[309,298],"id":20,"thread":"build-8"},{"duration":0,"stepId":"io.quarkus.deployment.steps.ReflectionDiagnosticProcessor#writeReflectionData","started":"06:50:37.645","dependents":[],"id":313,"thread":"build-36"},{"duration":0,"stepId":"io.quarkus.vertx.http.deployment.VertxHttpProcessor#shouldNotRemoveHttpServerOptionsCustomizers","started":"06:50:35.990","dependents":[264,266],"id":59,"thread":"build-12"}],"started":"2023-07-06T06:50:35.937","items":[{"count":546,"class":"io.quarkus.deployment.builditem.ConfigDescriptionBuildItem"},{"count":137,"class":"io.quarkus.deployment.builditem.GeneratedClassBuildItem"},{"count":86,"class":"io.quarkus.deployment.builditem.nativeimage.ReflectiveClassBuildItem"},{"count":46,"class":"io.quarkus.deployment.builditem.MainBytecodeRecorderBuildItem"},{"count":32,"class":"io.quarkus.deployment.builditem.nativeimage.ReflectiveHierarchyBuildItem"},{"count":32,"class":"io.quarkus.deployment.builditem.StaticBytecodeRecorderBuildItem"},{"count":32,"class":"io.quarkus.arc.deployment.SyntheticBeanBuildItem"},{"count":30,"class":"io.quarkus.vertx.http.deployment.devmode.console.DevTemplatePathBuildItem"},{"count":28,"class":"io.quarkus.deployment.builditem.nativeimage.RuntimeInitializedClassBuildItem"},{"count":26,"class":"io.quarkus.vertx.http.deployment.RouteBuildItem"},{"count":21,"class":"io.quarkus.arc.deployment.AdditionalBeanBuildItem"},{"count":19,"class":"io.quarkus.devconsole.spi.DevConsoleRouteBuildItem"},{"count":14,"class":"io.quarkus.deployment.builditem.RunTimeConfigurationDefaultBuildItem"},{"count":13,"class":"io.quarkus.resteasy.common.spi.ResteasyJaxrsProviderBuildItem"},{"count":10,"class":"io.quarkus.deployment.builditem.HotDeploymentWatchedFileBuildItem"},{"count":9,"class":"io.quarkus.deployment.builditem.CapabilityBuildItem"},{"count":8,"class":"io.quarkus.deployment.logging.LogCleanupFilterBuildItem"},{"count":8,"class":"io.quarkus.resteasy.server.common.spi.AllowedJaxRsAnnotationPrefixBuildItem"},{"count":8,"class":"io.quarkus.arc.deployment.UnremovableBeanBuildItem"},{"count":7,"class":"io.quarkus.deployment.pkg.builditem.PackageTypeBuildItem"},{"count":6,"class":"io.quarkus.deployment.builditem.SystemPropertyBuildItem"},{"count":6,"class":"io.quarkus.vertx.http.deployment.devmode.NotFoundPageDisplayableEndpointBuildItem"},{"count":6,"class":"io.quarkus.deployment.builditem.nativeimage.NativeImageSystemPropertyBuildItem"},{"count":5,"class":"io.quarkus.devui.deployment.InternalPageBuildItem"},{"count":5,"class":"io.quarkus.arc.deployment.AnnotationsTransformerBuildItem"},{"count":5,"class":"io.quarkus.deployment.builditem.SuppressNonRuntimeConfigChangedWarningBuildItem"},{"count":5,"class":"io.quarkus.deployment.builditem.FeatureBuildItem"},{"count":5,"class":"io.quarkus.deployment.builditem.ConsoleCommandBuildItem"},{"count":5,"class":"io.quarkus.devui.spi.JsonRPCProvidersBuildItem"},{"count":5,"class":"io.quarkus.deployment.builditem.AdditionalIndexedClassesBuildItem"},{"count":4,"class":"io.quarkus.deployment.builditem.RunTimeConfigBuilderBuildItem"},{"count":4,"class":"io.quarkus.arc.deployment.BeanDefiningAnnotationBuildItem"},{"count":4,"class":"io.quarkus.devconsole.spi.DevConsoleTemplateInfoBuildItem"},{"count":3,"class":"io.quarkus.vertx.http.deployment.FilterBuildItem"},{"count":3,"class":"io.quarkus.deployment.builditem.StaticInitConfigBuilderBuildItem"},{"count":3,"class":"io.quarkus.deployment.builditem.nativeimage.ReflectiveMethodBuildItem"},{"count":3,"class":"io.quarkus.jackson.spi.ClassPathJacksonModuleBuildItem"},{"count":3,"class":"io.quarkus.devconsole.spi.DevConsoleRuntimeTemplateInfoBuildItem"},{"count":3,"class":"io.quarkus.vertx.http.deployment.HttpSecurityPolicyBuildItem"},{"count":3,"class":"io.quarkus.vertx.http.deployment.webjar.WebJarBuildItem"},{"count":3,"class":"io.quarkus.devui.deployment.BuildTimeConstBuildItem"},{"count":3,"class":"io.quarkus.deployment.builditem.nativeimage.ReflectiveFieldBuildItem"},{"count":3,"class":"io.quarkus.deployment.builditem.AdditionalApplicationArchiveMarkerBuildItem"},{"count":3,"class":"io.quarkus.deployment.builditem.ServiceStartBuildItem"},{"count":2,"class":"io.quarkus.devui.deployment.DevUIWebJarBuildItem"},{"count":2,"class":"io.quarkus.deployment.builditem.ShutdownListenerBuildItem"},{"count":2,"class":"io.quarkus.deployment.builditem.ObjectSubstitutionBuildItem"},{"count":2,"class":"io.quarkus.arc.deployment.AutoAddScopeBuildItem"},{"count":2,"class":"io.quarkus.devui.spi.buildtime.QuteTemplateBuildItem"},{"count":2,"class":"io.quarkus.deployment.builditem.nativeimage.NativeImageConfigBuildItem"},{"count":2,"class":"io.quarkus.deployment.builditem.BytecodeTransformerBuildItem"},{"count":2,"class":"io.quarkus.deployment.dev.testing.TestListenerBuildItem"},{"count":2,"class":"io.quarkus.deployment.builditem.BytecodeRecorderObjectLoaderBuildItem"},{"count":2,"class":"io.quarkus.devui.deployment.DevUIRoutesBuildItem"},{"count":2,"class":"io.quarkus.devui.spi.buildtime.StaticContentBuildItem"},{"count":2,"class":"io.quarkus.devui.deployment.InternalImportMapBuildItem"},{"count":2,"class":"io.quarkus.deployment.builditem.LogCategoryBuildItem"},{"count":1,"class":"io.quarkus.devui.deployment.MvnpmBuildItem"},{"count":1,"class":"io.quarkus.deployment.builditem.AnnotationProxyBuildItem"},{"count":1,"class":"io.quarkus.deployment.builditem.TransformedClassesBuildItem"},{"count":1,"class":"io.quarkus.vertx.http.deployment.spi.StaticResourcesBuildItem"},{"count":1,"class":"io.quarkus.arc.deployment.devui.ArcBeanInfoBuildItem"},{"count":1,"class":"io.quarkus.deployment.console.ConsoleInstalledBuildItem"},{"count":1,"class":"io.quarkus.arc.deployment.BeanDiscoveryFinishedBuildItem"},{"count":1,"class":"io.quarkus.resteasy.common.spi.ResteasyConfigBuildItem"},{"count":1,"class":"io.quarkus.deployment.builditem.RunTimeConfigurationProxyBuildItem"},{"count":1,"class":"io.quarkus.arc.deployment.SynthesisFinishedBuildItem"},{"count":1,"class":"io.quarkus.vertx.http.deployment.DefaultRouteBuildItem"},{"count":1,"class":"io.quarkus.vertx.core.deployment.EventLoopCountBuildItem"},{"count":1,"class":"io.quarkus.resteasy.common.deployment.JaxrsProvidersToRegisterBuildItem"},{"count":1,"class":"io.quarkus.vertx.core.deployment.CoreVertxBuildItem"},{"count":1,"class":"io.quarkus.arc.deployment.BuildCompatibleExtensionsBuildItem"},{"count":1,"class":"io.quarkus.devui.deployment.ThemeVarsBuildItem"},{"count":1,"class":"io.quarkus.deployment.builditem.nativeimage.ReflectiveHierarchyIgnoreWarningBuildItem"},{"count":1,"class":"io.quarkus.arc.deployment.InterceptorResolverBuildItem"},{"count":1,"class":"io.quarkus.vertx.http.deployment.InitialRouterBuildItem"},{"count":1,"class":"io.quarkus.deployment.dev.ExceptionNotificationBuildItem"},{"count":1,"class":"io.quarkus.arc.deployment.ValidationPhaseBuildItem"},{"count":1,"class":"io.quarkus.netty.deployment.EventLoopSupplierBuildItem"},{"count":1,"class":"io.quarkus.arc.deployment.BeanArchiveIndexBuildItem"},{"count":1,"class":"io.quarkus.deployment.builditem.ConsoleFormatterBannerBuildItem"},{"count":1,"class":"io.quarkus.arc.deployment.SuppressConditionGeneratorBuildItem"},{"count":1,"class":"io.quarkus.deployment.builditem.ApplicationArchivesBuildItem"},{"count":1,"class":"io.quarkus.deployment.BooleanSupplierFactoryBuildItem"},{"count":1,"class":"io.quarkus.deployment.builditem.ContextHandlerBuildItem"},{"count":1,"class":"io.quarkus.arc.deployment.TransformedAnnotationsBuildItem"},{"count":1,"class":"io.quarkus.deployment.builditem.DevServicesLauncherConfigResultBuildItem"},{"count":1,"class":"io.quarkus.deployment.builditem.GeneratedFileSystemResourceHandledBuildItem"},{"count":1,"class":"io.quarkus.deployment.pkg.builditem.OutputTargetBuildItem"},{"count":1,"class":"io.quarkus.resteasy.deployment.ResteasyJaxrsConfigBuildItem"},{"count":1,"class":"io.quarkus.resteasy.server.common.spi.ResteasyJaxrsConfigBuildItem"},{"count":1,"class":"io.quarkus.arc.deployment.PreBeanContainerBuildItem"},{"count":1,"class":"io.quarkus.arc.deployment.InjectionPointTransformerBuildItem"},{"count":1,"class":"io.quarkus.deployment.builditem.ThreadFactoryBuildItem"},{"count":1,"class":"io.quarkus.vertx.http.deployment.devmode.console.DevConsoleProcessor$HistoryHandlerBuildItem"},{"count":1,"class":"io.quarkus.deployment.builditem.ApplicationIndexBuildItem"},{"count":1,"class":"io.quarkus.vertx.http.deployment.webjar.WebJarResultsBuildItem"},{"count":1,"class":"io.quarkus.arc.deployment.StereotypeRegistrarBuildItem"},{"count":1,"class":"io.quarkus.vertx.http.deployment.NonApplicationRootPathBuildItem"},{"count":1,"class":"io.quarkus.vertx.http.deployment.VertxWebRouterBuildItem"},{"count":1,"class":"io.quarkus.deployment.builditem.CombinedIndexBuildItem"},{"count":1,"class":"io.quarkus.devui.deployment.JsonRPCMethodsBuildItem"},{"count":1,"class":"io.quarkus.deployment.Capabilities"},{"count":1,"class":"io.quarkus.arc.deployment.GeneratedBeanBuildItem"},{"count":1,"class":"io.quarkus.devui.deployment.ExtensionsBuildItem"},{"count":1,"class":"io.quarkus.deployment.logging.LoggingSetupBuildItem"},{"count":1,"class":"io.quarkus.deployment.builditem.ExecutorBuildItem"},{"count":1,"class":"io.quarkus.deployment.builditem.WebSocketLogHandlerBuildItem"},{"count":1,"class":"io.quarkus.resteasy.common.deployment.ResteasyInjectionReadyBuildItem"},{"count":1,"class":"io.quarkus.smallrye.context.deployment.spi.ThreadContextProviderBuildItem"},{"count":1,"class":"io.quarkus.arc.deployment.BeanRegistrationPhaseBuildItem"},{"count":1,"class":"io.quarkus.arc.deployment.ObserverRegistrationPhaseBuildItem"},{"count":1,"class":"io.quarkus.deployment.builditem.ApplicationClassNameBuildItem"},{"count":1,"class":"io.quarkus.deployment.builditem.nativeimage.NativeImageResourceBuildItem"},{"count":1,"class":"io.quarkus.deployment.builditem.StreamingLogHandlerBuildItem"},{"count":1,"class":"io.quarkus.vertx.http.deployment.SecurityInformationBuildItem"},{"count":1,"class":"io.quarkus.deployment.dev.DisableInstrumentationForIndexPredicateBuildItem"},{"count":1,"class":"io.quarkus.resteasy.server.common.deployment.ResteasyServerConfigBuildItem"},{"count":1,"class":"io.quarkus.vertx.deployment.VertxBuildItem"},{"count":1,"class":"io.quarkus.arc.deployment.BeanContainerBuildItem"},{"count":1,"class":"io.quarkus.arc.deployment.CurrentContextFactoryBuildItem"},{"count":1,"class":"io.quarkus.deployment.ide.EffectiveIdeBuildItem"},{"count":1,"class":"io.quarkus.resteasy.deployment.ResteasyStandaloneBuildStep$ResteasyStandaloneBuildItem"},{"count":1,"class":"io.quarkus.deployment.pkg.builditem.CurateOutcomeBuildItem"},{"count":1,"class":"io.quarkus.vertx.http.deployment.HttpRootPathBuildItem"},{"count":1,"class":"io.quarkus.deployment.builditem.ConfigurationBuildItem"},{"count":1,"class":"io.quarkus.deployment.steps.CapabilityAggregationStep$CapabilitiesConfiguredInDescriptorsBuildItem"},{"count":1,"class":"io.quarkus.deployment.builditem.ApplicationStartBuildItem"},{"count":1,"class":"io.quarkus.deployment.builditem.ApplicationClassPredicateBuildItem"},{"count":1,"class":"io.quarkus.vertx.http.deployment.BodyHandlerBuildItem"},{"count":1,"class":"io.quarkus.deployment.builditem.LogCategoryMinLevelDefaultsBuildItem"},{"count":1,"class":"io.quarkus.deployment.builditem.GeneratedResourceBuildItem"},{"count":1,"class":"io.quarkus.arc.deployment.ContextRegistrationPhaseBuildItem"},{"count":1,"class":"io.quarkus.arc.deployment.ConfigInjectionStaticInitBuildItem"},{"count":1,"class":"io.quarkus.arc.deployment.CustomScopeAnnotationsBuildItem"},{"count":1,"class":"io.quarkus.deployment.builditem.IOThreadDetectorBuildItem"},{"count":1,"class":"io.quarkus.deployment.builditem.SslNativeConfigBuildItem"},{"count":1,"class":"io.quarkus.resteasy.server.common.deployment.ResteasyDeploymentBuildItem"},{"count":1,"class":"io.quarkus.devui.spi.page.CardPageBuildItem"},{"count":1,"class":"io.quarkus.arc.deployment.AutoInjectAnnotationBuildItem"},{"count":1,"class":"io.quarkus.arc.deployment.CompletedApplicationClassPredicateBuildItem"},{"count":1,"class":"io.quarkus.deployment.builditem.StaticInitConfigSourceFactoryBuildItem"},{"count":1,"class":"io.quarkus.deployment.builditem.ApplicationInfoBuildItem"},{"count":1,"class":"io.quarkus.deployment.ide.IdeRunningProcessBuildItem"},{"count":1,"class":"io.quarkus.deployment.ide.IdeFileBuildItem"},{"count":1,"class":"io.quarkus.deployment.builditem.MainClassBuildItem"}],"itemsCount":1325,"buildTarget":"quarkus-application"}